{
  "version": "7",
  "dialect": "postgresql",
  "entries": [
    {
      "idx": 0,
      "version": "7",
      "when": 1775821121070,
      "tag": "0000_cynical_jackpot",
      "breakpoints": true
    },
    {
      "idx": 1,
      "version": "7",
      "when": 1775865600000,
      "tag": "0001_user_tokens",
      "breakpoints": false
    },
    {
      "idx": 2,
      "version": "7",
      "when": 1776542400000,
      "tag": "0002_github_oauth",
      "breakpoints": false
    },
    {
      "idx": 3,
      "version": "7",
      "when": 1776700800000,
      "tag": "0003_fix_pr_url",
      "breakpoints": false
    }
  ]
}
